django-loggable/__init__.py
django-loggable/admin.py
django-loggable/models.py
django_loggable/__init__.py
django_loggable/admin.py
django_loggable/models.py
django_loggable-0.3.dist-info/METADATA
django_loggable-0.3.dist-info/RECORD
django_loggable-0.3.dist-info/WHEEL
django_loggable-0.3.dist-info/top_level.txt
