Metadata-Version: 2.1
Name: django-loggable
Version: 0.3
Summary: this library adds 'created_at', 'updated_at' and 'delete_at'  fields like a rail apps in django, also added soft delete method
Home-page: https://github.com/drneox/django_loggable
Author: Carlos Ganoza Plasencia
Author-email: cganozap@gmail.com
License: GPL
Keywords: django created_at updated_at deleted_at fields models django-admin
Platform: UNKNOWN
